contort/__init__.py
contort/contort.py
contort-1.3.0.dist-info/LICENSE
contort-1.3.0.dist-info/METADATA
contort-1.3.0.dist-info/WHEEL
contort-1.3.0.dist-info/entry_points.txt
contort-1.3.0.dist-info/top_level.txt
contort-1.3.0.dist-info/RECORD
