Metadata-Version: 2.1
Name: contort
Version: 1.3.0
Summary: COnTROT (COmprehensive Transcriptomic ORganizational Tool) is a program that will download and organize all expression data in GEO related to a search result, commonly an organism.
Home-page: https://github.com/GLBRC/contort
Author: Kevin Myers
Author-email: kmyers2@wisc.edu
License: MIT
Platform: UNKNOWN
Classifier: Programming Language :: Python :: 3.6
Classifier: Programming Language :: R
Classifier: License :: OSI Approved :: MIT License
Classifier: Operating System :: OS Independent
Classifier: Intended Audience :: Science/Research
Classifier: Topic :: Scientific/Engineering :: Bio-Informatics
Requires-Python: >=3.6
Requires-Dist: markdown (>=3.1.1)
Requires-Dist: biopython (>=1.74)
Requires-Dist: pandas (>=0.25.1)
Requires-Dist: GEOparse (>=2.0.1)
